nlp_automl/__init__.py
nlp_automl/auto_ml_pipeline.py
nlp_automl/base.py
nlp_automl/datatypes.py
nlp_automl/method/__init__.py
nlp_automl/method/base.py
nlp_automl/method/boosting.py
nlp_automl/method/log_reg.py
nlp_automl/method/rand_forest.py
nlp_automl/preprocess/__init__.py
nlp_automl/preprocess/base.py
nlp_automl/preprocess/basic.py
nlp_automl/preprocess/lemmatizer.py
nlp_automl/preprocess/stemmer.py
nlp_automl/py.typed
nlp_automl/vectorizer/__init__.py
nlp_automl/vectorizer/base.py
nlp_automl/vectorizer/count.py
nlp_automl/vectorizer/fast_text.py
nlp_automl/vectorizer/tf_idf.py
nlp_automl-0.5.dist-info/METADATA
nlp_automl-0.5.dist-info/WHEEL
nlp_automl-0.5.dist-info/RECORD
